{"id":"29c1cdb1-bf0c-4f27-bb52-b99f040e8f53","name":"Switched to a sole application (app 1)","templateType":"email","createdAt":1622725144.000000000,"updatedAt":1657189984.996230000,"createdBy":null,"version":12,"body":"Dear ((first name)) ((last name)),\r\n\r\nYou have ended your joint application ((isDivorce??for divorce))((isDissolution??to end your civil partnership)). Your ((partner)) has been notified by email.\r\n\r\nThey have not been given a reason so you may want to contact them to explain, if it's safe to do so.  \r\n\r\nDivorce and Dissolution\r\nHM Courts & Tribunals Service\r\ndivorcecase@justice.gov.uk\r\n0300 303 0642 (Monday to Friday, 8am to 6pm)\r\n\r\nYour feedback helps improve this service for others: https://www.smartsurvey.co.uk/s/Divorce_Feedback/?pageurl=/email","subject":"You have ended your joint ((isDivorce??divorce application))((isDissolution??application to end your civil partnership))","personalisation":{"last name":{"required":true},"first name":{"required":true},"partner":{"required":true},"isDissolution":{"required":true},"isDivorce":{"required":true}},"letterContactBlock":null}