{"id":"700d4e14-7eae-4219-b2e6-be01c31e071f","name":"You can apply for a final order (applicant) JOINT and SOLE","templateType":"email","createdAt":1634304829.000000000,"updatedAt":1662629179.345143000,"createdBy":null,"version":13,"body":"Case number: ((reference number))\r\n\r\nDear ((first name)) ((last name))\r\n\r\nYou can now apply for a 'final order'. This is a court document that will legally end your ((isDivorce??marriage))((isDissolution??civil partnership)). \r\n\r\n((joint conditional order??This is a joint application so both you and your ))((husbandJoint??husband))((wifeJoint??wife))((civilPartnerJoint??civil partner))((joint conditional order?? have to apply. They have been sent this email too.))\r\n\r\n^If you have not yet finished any negotiations or legal proceedings about your money, property or other assets then you should seek legal advice before ((isDivorce??finalising your divorce.))((isDissolution??ending your civil partnership.))\r\n\r\nSign in to your HMCTS account and apply for a 'final order': ((signin url))\r\n\r\nDivorce and Dissolution \r\nHM Courts & Tribunals Service \r\ndivorcecase@justice.gov.uk\r\n0300 303 0642 (Monday to Friday, 8am to 6pm) \r\n\r\nYour feedback helps improve this service for others: https://www.smartsurvey.co.uk/s/Divorce_Feedback/?pageurl=/email.","subject":"((isReminder??Reminder: ))Action required: your ((isDivorce??divorce application:))((isDissolution??application to end your civil partnership:))","personalisation":{"signin url":{"required":true},"isReminder":{"required":true},"husbandJoint":{"required":true},"last name":{"required":true},"first name":{"required":true},"reference number":{"required":true},"isDissolution":{"required":true},"civilPartnerJoint":{"required":true},"isDivorce":{"required":true},"joint conditional order":{"required":true},"wifeJoint":{"required":true}},"letterContactBlock":null}