{"id":"f7929730-decd-41fd-b596-de71699f6c7e","name":"Joint application ended (app 2)","templateType":"email","createdAt":1622726268.000000000,"updatedAt":1657190423.483753000,"createdBy":null,"version":13,"body":"Your ((partner)) has ended the joint application ((isDivorce??for divorce))((isDissolution??to end your civil partnership)). You cannot access the application anymore. \r\n\r\nThey were not asked to provide a reason. You could contact them and ask them why, if it's safe to do so. \r\n\r\nEither you or your ((partner)) can create and submit a new application. \r\n\r\nDivorce and Dissolution\r\nHM Courts & Tribunals Service\r\ndivorcecase@justice.gov.uk\r\n0300 303 0642 (Monday to Friday, 8am to 6pm)\r\n\r\nYour feedback helps improve this service for others: https://www.smartsurvey.co.uk/s/Divorce_Feedback/?pageurl=/email","subject":"Your ((partner)) has ended the joint application ((isDivorce??for your divorce))((isDissolution??to end your civil partnership))","personalisation":{"partner":{"required":true},"isDissolution":{"required":true},"isDivorce":{"required":true}},"letterContactBlock":null}